<?xml version="1.0" encoding="UTF-8"?>
<r>
   <e>
      <lg>
         <l pos="pron-refl">ас</l>
      </lg>
      <mg MNo="1">
         <tg xml:lang="ru">
            <t pos="A">свой, собственный</t>
         </tg>
      </mg>
      <mg MNo="2">
         <tg xml:lang="ru">
            <t pos="A">свой, своего изготовления, домашний</t>
         </tg>
      </mg>
      <mg MNo="3">
         <tg xml:lang="ru">
            <t pos="A">свой, родной</t>
         </tg>
      </mg>
      <mg MNo="4">
         <tg xml:lang="ru">
            <t pos="A">свой, местный</t>
         </tg>
      </mg>
      <mg MNo="5">
         <tg xml:lang="ru">
            <t>себя</t>
            <re>чаще употр. с послелогами; в отношении лица может конкретизироваться притяж. суффиксами, присоединяемыми к послелогу</re>
         </tg>
      </mg>
   </e>
   <e>
      <lg>
         <l pos="pron-refl">аслад</l>
      </lg>
      <mg MNo="1">
         <tg xml:lang="ru">
            <t/>
         </tg>
      </mg>
      <mg MNo="2">
         <tg xml:lang="ru">
            <t pos="PRON-PERS">свой</t>
            <t pos="PRON-PERS">твой</t>
         </tg>
      </mg>
   </e>
   <e>
      <lg>
         <l pos="pron-refl">асладор</l>
      </lg>
      <mg>
         <tg xml:lang="ru">
            <t>своя сторона</t>
            <t>родная сторона</t>
         </tg>
      </mg>
   </e>
   <e>
      <lg>
         <l pos="pron-refl">асладорсянь</l>
      </lg>
      <mg>
         <tg xml:lang="ru">
            <t>от себя</t>
         </tg>
      </mg>
   </e>
   <e>
      <lg>
         <l pos="pron-refl">асладорын</l>
      </lg>
      <mg>
         <tg xml:lang="ru">
            <t>на родной стороне</t>
         </tg>
      </mg>
   </e>
   <e>
      <lg>
         <l pos="pron-refl">асладорӧ</l>
      </lg>
      <mg MNo="1">
         <tg xml:lang="ru">
            <t>на свою сторону</t>
         </tg>
      </mg>
      <mg MNo="2">
         <tg xml:lang="ru">
            <t>в свою пользу</t>
         </tg>
      </mg>
   </e>
   <e>
      <lg>
         <l pos="pron-refl">аслам</l>
      </lg>
      <mg MNo="1">
         <tg xml:lang="ru">
            <t/>
         </tg>
      </mg>
      <mg MNo="2">
         <tg xml:lang="ru">
            <t>свой, мне принадлежащий</t>
         </tg>
      </mg>
   </e>
   <e>
      <lg>
         <l pos="pron-refl">асланыд</l>
      </lg>
      <mg MNo="2">
         <tg xml:lang="ru">
            <t>свой, ваш, вам принадлежащий</t>
         </tg>
      </mg>
   </e>
   <e>
      <lg>
         <l pos="pron-refl">асланыдладор</l>
      </lg>
      <mg>
         <tg xml:lang="ru">
            <t>ваша сторона</t>
         </tg>
      </mg>
   </e>
   <e>
      <lg>
         <l pos="pron-refl">асланым</l>
      </lg>
      <mg MNo="1">
         <tg xml:lang="ru">
            <t/>
         </tg>
      </mg>
      <mg MNo="2">
         <tg xml:lang="ru">
            <t>свой, наш, нам принадлежащий</t>
         </tg>
      </mg>
   </e>
   <e>
      <lg>
         <l pos="pron-refl">асланымладор</l>
      </lg>
      <mg>
         <tg xml:lang="ru">
            <t>своя (наша) сторона</t>
         </tg>
      </mg>
   </e>
   <e>
      <lg>
         <l pos="pron-refl">асланыс</l>
      </lg>
      <mg MNo="1">
         <tg xml:lang="ru">
            <t/>
         </tg>
      </mg>
      <mg MNo="2">
         <tg xml:lang="ru">
            <t>свой, их, им принадлежащий</t>
         </tg>
      </mg>
   </e>
   <e>
      <lg>
         <l pos="pron-refl">асланысладор</l>
      </lg>
      <mg>
         <tg xml:lang="ru">
            <t>своя (их) сторона</t>
         </tg>
      </mg>
   </e>
   <e>
      <lg>
         <l pos="pron-refl">аслань</l>
      </lg>
      <mg MNo="1">
         <tg xml:lang="ru">
            <t>на свою сторону</t>
         </tg>
      </mg>
      <mg MNo="2">
         <tg xml:lang="ru">
            <t>к себе</t>
         </tg>
      </mg>
   </e>
   <e>
      <lg>
         <l pos="pron-refl">аслас</l>
      </lg>
      <mg MNo="1">
         <tg xml:lang="ru">
            <t/>
         </tg>
      </mg>
      <mg MNo="2">
         <tg xml:lang="ru">
            <t>свой, его, ему принадлежащий</t>
         </tg>
      </mg>
   </e>
   <e>
      <lg>
         <l pos="pron-refl">ассьыд</l>
      </lg>
      <mg MNo="1">
         <tg xml:lang="ru">
            <t/>
         </tg>
      </mg>
      <mg MNo="2">
         <tg xml:lang="ru">
            <t>свой, твой</t>
         </tg>
      </mg>
   </e>
   <e>
      <lg>
         <l pos="pron-refl">ассьым</l>
      </lg>
      <mg MNo="1">
         <tg xml:lang="ru">
            <t/>
         </tg>
      </mg>
      <mg MNo="2">
         <tg xml:lang="ru">
            <t>свой, мой</t>
         </tg>
      </mg>
   </e>
   <e>
      <lg>
         <l pos="pron-refl">ассьыныд</l>
      </lg>
      <mg MNo="1">
         <tg xml:lang="ru">
            <t/>
         </tg>
      </mg>
      <mg MNo="2">
         <tg xml:lang="ru">
            <t>свой, ваш</t>
         </tg>
      </mg>
   </e>
   <e>
      <lg>
         <l pos="pron-refl">ассьыным</l>
      </lg>
      <mg MNo="1">
         <tg xml:lang="ru">
            <t/>
         </tg>
      </mg>
      <mg MNo="2">
         <tg xml:lang="ru">
            <t>свой, наш</t>
         </tg>
      </mg>
   </e>
   <e>
      <lg>
         <l pos="pron-refl">ассьыныс</l>
      </lg>
      <mg MNo="1">
         <tg xml:lang="ru">
            <t/>
         </tg>
      </mg>
      <mg MNo="2">
         <tg xml:lang="ru">
            <t>свой, их</t>
         </tg>
      </mg>
   </e>
   <e>
      <lg>
         <l pos="pron-refl">ассьыс</l>
      </lg>
      <mg MNo="1">
         <tg xml:lang="ru">
            <t/>
         </tg>
      </mg>
      <mg MNo="2">
         <tg xml:lang="ru">
            <t>свой, его</t>
         </tg>
      </mg>
   </e>
   <e>
      <lg>
         <l pos="pron-refl">астӧг</l>
      </lg>
      <mg MNo="2">
         <tg xml:lang="ru">
            <t>заочно</t>
         </tg>
      </mg>
   </e>
   <e>
      <lg>
         <l pos="pron-refl">асьныд</l>
      </lg>
      <mg>
         <tg xml:lang="ru">
            <t>вы сами</t>
         </tg>
      </mg>
   </e>
   <e>
      <lg>
         <l pos="pron-refl">асьным</l>
      </lg>
      <mg>
         <tg xml:lang="ru">
            <t>мы сами</t>
         </tg>
      </mg>
   </e>
   <e>
      <lg>
         <l pos="pron-refl">асьныс</l>
      </lg>
      <mg>
         <tg xml:lang="ru">
            <t>они сами</t>
         </tg>
      </mg>
   </e>
   <e>
      <lg>
         <l pos="pron-refl">ачыд</l>
      </lg>
      <mg>
         <tg xml:lang="ru">
            <t pos="PHRASE-PRON">ты сам</t>
         </tg>
      </mg>
   </e>
   <e>
      <lg>
         <l pos="pron-refl">ачым</l>
      </lg>
      <mg>
         <tg xml:lang="ru">
            <t pos="PHRASE-PRON">я сам</t>
         </tg>
      </mg>
   </e>
   <e>
      <lg>
         <l pos="pron-refl">ачыс</l>
      </lg>
      <mg>
         <tg xml:lang="ru">
            <t pos="PHRASE-PRON">он сам</t>
         </tg>
         <tg xml:lang="ru">
            <t pos="PHRASE-PRON">она сама</t>
         </tg>
         <tg xml:lang="ru">
            <t pos="PHRASE-PRON">оно само</t>
         </tg>
      </mg>
   </e>
</r>