<?xml version="1.0" encoding="UTF-8"?>
<dict xsi:noNamespaceSchemaLocation="../dict.xsd"
      xmlns:xsi="http://www.w3.org/2001/XMLSchema-instance"
      xmlns:xs="http://www.w3.org/2001/XMLSchema">
  <!--
<entry exclude="fst"> -->

  <!-- <lemma>CiprianAndTrond</lemma> -->

  <!-- <stem>FixThis</stem> -->

  <!-- <contlex>#</contlex> -->

  <!-- <pos>N</pos> -->

  <!-- -->

  <!-- </entry>-->

  <entry exclude="fst">
    <lemma>ме</lemma>

    <stem></stem>

    <contlex>PRON-PERS-SG1-NOM</contlex>

    <pos>PRON-PERS</pos>

    <e>
      <mg>
        <m>
          <head><!--<b>(мен</b> <i>- полная основа в косв. п.)</i>--></head>

          <tg lang="ru"><t pos="PRON-PERS">я</t></tg>
        </m>

        <xg>
          <x>ме дась</x>

          <xtg lang="ru"><xt pos="PRON-PERS">я готов</xt></xtg>
        </xg>

        <xg>
          <x>метӧ тӧда</x>

          <xtg lang="ru"><xt pos="PRON-PERS">я-то знаю</xt></xtg>
        </xg>

        <xg>
          <x>тайӧ ме, восьты</x>

          <xtg lang="ru"><xt pos="PRON-PERS">это я, открой</xt></xtg>
        </xg>

        <xg>
          <x>Ме пӧ и эм</x>

          <xtg lang="ru"><xt pos="PRON-PERS">я не я</xt></xtg>
        </xg>

        <xg>
          <x>ме пӧ и мортыс</x>

          <xtg lang="ru"><xt pos="PRON-PERS">нет человека лучше меня</xt><re>о человеке, составившем о себе преувеличенно высокое мнение</re></xtg>
        </xg>
      </mg>

      <mg>
        <m>
          <head><com>редко в роли притяж. мест.</com></head>

          <tg lang="ru"><t pos="PRON-PERS">мой</t></tg>

          <assoc MNo="1" assocType="see">менам</assoc>
        </m>

        <xg>
          <x></x>

          <xtg lang="ru"><xt></xt></xtg>
        </xg>
      </mg>

      <mg>
        <m>
          <head></head>

          <tg lang="ru"><t></t></tg>
        </m>

        <xg>
          <x>ме бердӧ ляскысис</x>

          <xtg lang="ru"><xt pos="PRON-PERS">он прижался ко мне</xt></xtg>
        </xg>

        <xg>
          <x>ме бокын</x>

          <xtg lang="ru"><xt pos="PRON-PERS">рядом со мной</xt></xtg>
        </xg>

        <xg>
          <x>тэ ме вылӧ эн надейтчы</x>

          <xtg lang="ru"><xt pos="PRON-PERS">ты на меня не
          рассчитывай</xt></xtg>
        </xg>

        <xg>
          <x>ме дінӧ пуксьы</x>

          <xtg lang="ru"><xt pos="PRON-PERS">садись возле меня</xt></xtg>
        </xg>

        <xg>
          <x>ме дінын олӧ</x>

          <xtg lang="ru"><xt pos="PRON-PERS">он живёт около меня</xt></xtg>
        </xg>

        <xg>
          <x>ме дор сувт</x>

          <xtg lang="ru"><xt pos="PRON-PERS">заступись за меня</xt></xtg>
        </xg>

        <xg>
          <x>ме дырйи татшӧм сёрни эз вӧвлы</x>

          <xtg lang="ru"><xt pos="PRON-PERS">при мне (в моём присутствии)
          такого разговора не было</xt></xtg>
        </xg>

        <xg>
          <x>ме кузя</x>

          <xtg lang="ru"><xt pos="PRON-PERS">с меня ростом</xt></xtg>

          <xtg lang="ru"><xt pos="PRON-PERS">ради меня</xt></xtg>
        </xg>

        <xg>
          <x>ме ног</x>

          <xtg lang="ru"><xt>по-моему</xt></xtg>
        </xg>

        <xg>
          <x>ме ногӧн</x>

          <xtg lang="ru"><xt>по-моему</xt></xtg>
        </xg>

        <xg>
          <x>вӧч ме ног</x>

          <xtg lang="ru"><xt>сделай по-моему</xt></xtg>
        </xg>

        <xg>
          <x>ме думысь</x>

          <xtg lang="ru"><xt>по-моему</xt></xtg>
        </xg>

        <xg>
          <x>ме думысь талун зэрмас</x>

          <xtg lang="ru"><xt>по-моему, сегодня будет дождь</xt></xtg>
        </xg>

        <xg>
          <x>ме ордын олӧ</x>

          <xtg lang="ru"><xt>он живёт у меня</xt></xtg>
        </xg>

        <xg>
          <x>сійӧ локтіс ме ордӧ гӧститны</x>

          <xtg lang="ru"><xt>он приехал ко мне погостить</xt></xtg>
        </xg>

        <xg>
          <x>ме сайӧ дзебсьы</x>

          <xtg lang="ru"><xt>спрячься за меня</xt></xtg>
        </xg>

        <xg>
          <x>ме улын</x>

          <xtg lang="ru"><xt>подо мной</xt></xtg>
        </xg>

        <xg>
          <x>ме ог тӧд, код кодь тэ лоӧмыд</x>

          <xtg lang="ru"><xt>стал неузнаваемым (я не знаю, каким ты
          стал)</xt></xtg>
        </xg>

        <xg>
          <x>том дырйиыд мыйкӧ морт кодь вӧлін, а ӧні ме ог тӧд, код кодь
          лоӧмыд</x>

          <xtg lang="ru"><xt>в молодости ты был человеком, а теперь не знаю,
          каким ты стал</xt></xtg>
        </xg>

        <xg type="saying">
          <x>ме висьтала поп йылысь, а сійӧ пыр попаддя йылысь</x>

          <xtg lang="ru"><xt>я говорю о попе, а он твердит о
          попадье</xt></xtg>
        </xg>

        <xg>
          <x>кагасӧ ме ки вылӧ колис</x>

          <xtg lang="ru"><xt pos="PRON-PERS">ребёнка она оставила на моих
          руках</xt></xtg>
        </xg>

        <xg>
          <x>ставыс ме киын, кыдз кӧсъя, сідз и вӧча</x>

          <xtg lang="ru"><xt pos="PRON-PERS">всё в моих руках — как захочу,
          так и сделаю</xt></xtg>
        </xg>
      </mg>
    </e>
  </entry>

  <entry exclude="fst">
    <lemma>мекӧд</lemma>

    <stem></stem>

    <contlex></contlex>

    <pos>PRON-PERS</pos>

    <e>
      <mg>
        <m>
          <head></head>

          <tg lang="ru"><t pos="PRON-PERS">со мной</t></tg>
        </m>

        <xg>
          <x>мекӧд ветлам</x>

          <xtg lang="ru"><xt pos="PRON-PERS">сходим со мной</xt></xtg>
        </xg>
      </mg>
    </e>
  </entry>

  <entry exclude="fst">
    <lemma>мела</lemma>

    <stem></stem>

    <contlex></contlex>

    <pos>PRON-PERS</pos>

    <e>
      <mg>
        <m>
          <head></head>

          <tg lang="ru"><t pos="PRON-PERS">за мной</t></tg>
        </m>

        <xg>
          <x>мела воліс?</x>

          <xtg lang="ru"><xt pos="PRON-PERS">он за мной приходил?</xt></xtg>
        </xg>
      </mg>
    </e>
  </entry>

  <entry exclude="fst">
    <lemma>мелань</lemma>

    <stem></stem>

    <contlex></contlex>

    <pos>PRON-PERS</pos>

    <e>
      <mg>
        <m>
          <head></head>

          <tg lang="ru"><t pos="PRON-PERS"><com>прибл. п.</com>ко мне</t></tg>
        </m>

        <xg>
          <x>мелань бергӧдчы</x>

          <xtg lang="ru"><xt pos="PRON-PERS">повернись ко мне</xt></xtg>
        </xg>

        <xg>
          <x>сійӧ мелань восьлаліс</x>

          <xtg lang="ru"><xt pos="PRON-PERS">он шагал ко мне</xt></xtg>
        </xg>

        <xg>
          <x>сой нюжӧдіс мелань</x>

          <xtg lang="ru"><xt pos="PRON-PERS">он протянул ко мне
          руку</xt></xtg>
        </xg>
      </mg>
    </e>
  </entry>

  <entry exclude="fst">
    <lemma>мем</lemma>

    <stem>ме</stem>

    <contlex>PRON-PERS-SG1-DAT</contlex>

    <pos>PRON-PERS</pos>

    <e>
      <mg>
        <m>
          <head></head>

          <tg lang="ru"><t></t></tg>
        </m>
      </mg>
    </e>
  </entry>

  <entry exclude="fst">
    <lemma>мен</lemma>

    <stem>мен</stem>

    <contlex>PRON-PERS-SG1-DAT</contlex>

    <pos>PRON-PERS</pos>

    <e>
      <mg>
        <m>
          <head></head>

          <tg lang="ru"><t></t></tg>
        </m>
      </mg>
    </e>
  </entry>

  <entry exclude="fst">
    <lemma>менам</lemma>

    <stem>мен</stem>

    <contlex>PRON-PERS-SG1-GEN</contlex>

    <pos>PRON-PERS</pos>

    <e>
      <mg>
        <m>
          <head></head>

          <tg lang="ru"><t></t></tg>
        </m>

        <xg>
          <x>тайӧ менам аслам</x>

          <xtg lang="ru"><xt pos="PRON-PERS">это у меня своё</xt></xtg>
        </xg>

        <xg>
          <x>менам талун узьсьӧма</x>

          <xtg lang="ru"><xt pos="PRON-PERS">я сегодня проспал</xt></xtg>
        </xg>

        <xg>
          <x>менам тэныд вӧлі висьталӧма</x>

          <xtg lang="ru"><xt pos="PRON-PERS">мною тебе было сказано</xt></xtg>
        </xg>

        <xg>
          <x>менам ставыс сьӧрын и бӧрын</x>

          <xtg lang="ru"><xt>у меня всё при себе</xt></xtg>

          <com>ни семьи, ни хозяйства</com>
        </xg>

        <xg>
          <x>менам ӧти юрыс; кык кӧ вӧлі, ӧтисӧ вузавны позис</x>

          <xtg lang="ru"><xt pos="PRON-PERS">у меня одна голова; будь две, то
          одну можно было бы продать</xt></xtg>
        </xg>
      </mg>

      <mg>
        <m>
          <head><com>в роли притяж. мест.</com></head>

          <tg lang="ru"><t pos="PRON-PERS">мой</t></tg>
        </m>

        <xg>
          <x>менам бать-мам</x>

          <xtg lang="ru"><xt pos="PRON-PERS">мои родители</xt></xtg>
        </xg>

        <xg>
          <x>менам важся друг</x>

          <xtg lang="ru"><xt pos="PRON-PERS">мой старый друг</xt></xtg>
        </xg>

        <xg>
          <x>менам ныв-пи</x>

          <xtg lang="ru"><xt pos="PRON-PERS">мои дети</xt></xtg>
        </xg>

        <xg>
          <x>менам локтӧдз</x>

          <xtg lang="ru"><xt pos="PRON-PERS">до моего прихода</xt></xtg>
        </xg>

        <xg>
          <x>менам тшӧктӧм серти</x>

          <xtg lang="ru"><xt pos="PRON-PERS">по моему велению, по моему
          приказанию, по моему распоряжению</xt></xtg>
        </xg>

        <xg>
          <x>менам синва тэныд усьӧ</x>

          <xtg lang="ru"><xt pos="PRON-PERS">мои слёзы тебе
          отольются</xt></xtg>
        </xg>

        <xg>
          <x>тайӧ абу менам удж</x>

          <xtg lang="ru"><xt pos="PRON-PERS">это не моя работа</xt></xtg>
        </xg>
      </mg>
    </e>
  </entry>

  <entry exclude="fst">
    <lemma>менамтӧг</lemma>

    <stem>менам</stem>

    <contlex>PRON-PERS-SG1-CAR</contlex>

    <pos>PRON-PERS</pos>

    <e>
      <mg>
        <m>
          <head></head>

          <tg lang="ru"><t></t></tg>

          <assoc MNo="1" assocType="see">метӧг</assoc>
        </m>
      </mg>
    </e>
  </entry>

  <entry exclude="fst">
    <lemma>менлы</lemma>

    <stem>мен</stem>

    <contlex>PRON-PERS-SG1-DAT</contlex>

    <pos>PRON-PERS</pos>

    <e>
      <mg>
        <m>
          <head></head>

          <tg lang="ru"><t></t></tg>
        </m>

        <xg>
          <x>менлы вылӧ</x>

          <xtg lang="ru"><xt pos="PRON-PERS">для меня</xt></xtg>
        </xg>

        <xg>
          <x>менлы кодь</x>

          <xtg lang="ru"><xt pos="PRON-PERS">подходящий мне</xt></xtg>

          <xtg lang="ru"><xt pos="PRON-PERS">по мне</xt></xtg>
        </xg>

        <xg>
          <x>тайӧ шапкаыс менлы кодь</x>

          <xtg lang="ru"><xt pos="PRON-PERS">эта шапка по мне</xt></xtg>
        </xg>

        <xg>
          <x>тайӧс бать ньӧбӧма менлы вылӧ</x>

          <xtg lang="ru"><xt pos="PRON-PERS">это отец купил для
          меня</xt></xtg>
        </xg>
      </mg>
    </e>
  </entry>

  <entry exclude="fst">
    <lemma>менсьым</lemma>

    <stem>мен</stem>

    <contlex>PRON-PERS-SG1-ELA</contlex>

    <pos>PRON-PERS</pos>

    <e>
      <mg>
        <m>
          <head></head>

          <tg lang="ru"><t></t></tg>
        </m>

        <xg>
          <x>тэ менсьым юав</x>

          <xtg lang="ru"><xt pos="PRON-PERS">ты у меня спроси</xt></xtg>
        </xg>
      </mg>

      <mg>
        <m>
          <head></head>

          <tg lang="ru"><t pos="PRON-PERS">мой</t></tg>
        </m>

        <xg>
          <x>книгаӧс менсьым кодкӧ босьтӧма</x>

          <xtg lang="ru"><xt pos="PRON-PERS">кто-то взял мою книгу</xt></xtg>
        </xg>
      </mg>
    </e>
  </entry>

  <entry exclude="fst">
    <lemma>менсянь</lemma>

    <stem>мен</stem>

    <contlex>PRON-PERS-SG1-DAT</contlex>

    <pos>PRON-PERS</pos>

    <e>
      <mg>
        <m>
          <head></head>

          <tg lang="ru"><t></t></tg>
        </m>

        <xg>
          <x>месянь поклон висьтав</x>

          <xtg lang="ru"><xt pos="PRON-PERS">передай от меня привет</xt></xtg>
        </xg>

        <xg>
          <x>мый тэныд месянь колӧ?</x>

          <xtg lang="ru"><xt pos="PRON-PERS">что тебе от меня надо?</xt></xtg>
        </xg>
      </mg>
    </e>
  </entry>

  <entry exclude="fst">
    <lemma>меным</lemma>

    <stem>мен</stem>

    <contlex>PRON-PERS-SG1-DAT</contlex>

    <pos>PRON-PERS</pos>

    <e>
      <mg>
        <m>
          <head></head>

          <tg lang="ru"><t></t></tg>
        </m>

        <xg>
          <x>меным вылӧ</x>

          <xtg lang="ru"><xt pos="PRON-PERS">для меня</xt></xtg>
        </xg>

        <xg>
          <x>кодлы сійӧ шуис, меным али тэныд?</x>

          <xtg lang="ru"><xt pos="PRON-PERS">кому он сказал, мне или
          тебе?</xt></xtg>
        </xg>

        <xg>
          <x>меным гӧгӧрвоана лои</x>

          <xtg lang="ru"><xt pos="PRON-PERS">мне стало понятно</xt></xtg>
        </xg>

        <xg>
          <x>оз ков меным татшӧм лёк ёртыд</x>

          <xtg lang="ru"><xt pos="PRON-PERS">мне не нужен такой плохой
          друг</xt></xtg>
        </xg>

        <xg>
          <x>меным тайӧ дуб ва</x>

          <xtg lang="ru"><xt pos="PRON-PERS">это для меня пустяки</xt></xtg>

          <literal>
            <xtg lang="ru"><xt pos="PRON-PERS">это для меня пресная
            вода</xt></xtg>
          </literal>
        </xg>
      </mg>
    </e>
  </entry>

  <entry exclude="fst">
    <lemma>менӧ</lemma>

    <stem>мен</stem>

    <contlex>PRON-PERS-SG1-ACC</contlex>

    <pos>PRON-PERS</pos>

    <e>
      <mg>
        <m>
          <head></head>

          <tg lang="ru"><t></t></tg>
        </m>

        <xg>
          <x>коді менӧ юасьӧ?</x>

          <xtg lang="ru"><xt pos="PRON-PERS">кто меня спрашивает?</xt></xtg>
        </xg>

        <xg>
          <x>менӧ тэ тӧдан</x>

          <xtg lang="ru"><xt pos="PRON-PERS">ты меня знаешь</xt></xtg>
        </xg>

        <xg>
          <x>менӧ аслад доддьӧ эн пуксьӧд, ме абу тэ кодь</x>

          <xtg lang="ru"><xt>не меряй меня на свой аршин я не такой, как
          ты</xt></xtg>

          <literal>
            <xtg lang="ru"><xt>не усаживай меня в свои сани я не такой, как
            ты</xt></xtg>
          </literal>
        </xg>

        <xg type="riddle">
          <x>менӧ частӧ корӧны, виччысьӧны, а петкӧдча кӧ, ставыс
          дзебсьӧны</x>

          <xtg lang="ru"><xt pos="PRON-PERS">меня частенько просят, ждут, а
          как покажусь, прятаться начнут</xt></xtg>

          <answer>
            <x>зэр</x>

            <xtg lang="ru"><xt pos="PRON-PERS">дождь</xt></xtg>
          </answer>
        </xg>
      </mg>
    </e>
  </entry>

  <entry exclude="fst">
    <lemma>метӧг</lemma>

    <stem>мен</stem>

    <contlex>PRON-PERS-SG1-DAT</contlex>

    <pos>PRON-PERS</pos>

    <e>
      <mg>
        <m>
          <head></head>

          <tg lang="ru"><t pos="PRON-PERS">без меня</t></tg>
        </m>

        <xg>
          <x>метӧг волӧма, ме эг вӧв</x>

          <xtg lang="ru"><xt pos="PRON-PERS">он без меня приходил, меня не
          было</xt></xtg>
        </xg>
      </mg>
    </e>
  </entry>

  <entry exclude="fst">
    <lemma>меын</lemma>

    <stem></stem>

    <contlex></contlex>

    <pos>PRON-PERS</pos>

    <e>
      <mg>
        <m>
          <head></head>

          <tg lang="ru"><t pos="PRON-PERS">мест. п. от ме</t></tg>
        </m>

        <xg>
          <x>абу меын делӧыс</x>

          <xtg lang="ru"><xt pos="PRON-PERS">не во мне дело</xt></xtg>
        </xg>
      </mg>
    </e>
  </entry>

  <entry exclude="fst">
    <lemma>меысь</lemma>

    <stem></stem>

    <contlex></contlex>

    <pos>PRON-PERS</pos>

    <e>
      <mg>
        <m>
          <head></head>

          <tg lang="ru"><t></t></tg>
        </m>

        <xg>
          <x>мый тэныд меысь колӧ?</x>

          <xtg lang="ru"><xt pos="PRON-PERS">что тебе от меня надо?</xt></xtg>
        </xg>

        <xg>
          <x>меысь метӧм, тэысь тэтӧм</x>

          <xtg lang="ru"><xt pos="PRON-PERS">ни я к тебе, ни ты ко
          мне</xt><re>заявление о полном разрыве дружбы, связи</re></xtg>
        </xg>
      </mg>
    </e>
  </entry>

  <entry exclude="fst">
    <lemma>меям</lemma>

    <stem>мен</stem>

    <contlex>PRON-PERS-SG1-GEN</contlex>

    <pos>PRON-PERS</pos>

    <e>
      <mg>
        <m>
          <head><range>диал.</range></head>

          <tg lang="ru"><t></t></tg>

          <assoc MNo="1" assocType="see">менам</assoc>
        </m>
      </mg>
    </e>
  </entry>

  <entry exclude="fst">
    <lemma>меӧдз</lemma>

    <stem>ме</stem>

    <contlex>PRON-PERS-SG1-TER</contlex>

    <pos>PRON-PERS</pos>

    <e>
      <mg>
        <m>
          <head></head>

          <tg lang="ru"><t pos="PRON-PERS"><com>пред. п. от </com> ме</t></tg>
        </m>

        <xg>
          <x>кутшӧм тэныд меӧдз мог?</x>

          <xtg lang="ru"><xt pos="PRON-PERS">какое тебе до меня
          дело?</xt></xtg>
        </xg>
      </mg>
    </e>
  </entry>

  <entry exclude="fst">
    <lemma>ми</lemma>

    <stem></stem>

    <contlex>PRON-PERS-PL1-NOM</contlex>

    <pos>PRON-PERS</pos>

    <e>
      <mg>
        <m>
          <head></head>

          <tg lang="ru"><t></t></tg>
        </m>

        <xg>
          <x>ми ставӧн</x>

          <xtg lang="ru"><xt pos="PRON-PERS">все мы</xt></xtg>
        </xg>

        <xg>
          <x>лунсӧ тайӧс ми виччысим дыр</x>

          <xtg lang="ru"><xt pos="PRON-PERS">этого дня мы ждали
          давно</xt></xtg>
        </xg>

        <xg>
          <x>митӧ ог кольччӧй</x>

          <xtg lang="ru"><xt pos="PRON-PERS">мы-то не отстане</xt></xtg>
        </xg>

        <xg type="saying">
          <x>ми водз чеччывлам: кымӧра кӧ, шонді петтӧдз</x>

          <xtg lang="ru"><xt pos="PRON-PERS">мы рано встаём: если облачно, до
          восхода солнца</xt></xtg>
        </xg>

        <xg>
          <x>Ми вок, ми коддьӧм, ми вок коддьӧм, ми вок кодь</x>

          <xtg lang="ru"><xt pos="PRON-PERS">наш брат; вроде нашего
          брата</xt></xtg>
        </xg>

        <xg>
          <x>ми вок кодь нывка-зонкаяс</x>

          <xtg lang="ru"><xt pos="PRON-PERS">такие же, как мы, девочки и
          мальчики</xt></xtg>
        </xg>

        <xg>
          <x>ми вок коддьӧмтӧ найӧ морт туйӧ оз пуктыны</x>

          <xtg lang="ru"><xt pos="PRON-PERS">нашего брата они за человека не
          считают</xt></xtg>
        </xg>

        <xg>
          <x>ми коддьӧмыд сэн уна</x>

          <xtg lang="ru"><xt pos="PRON-PERS">нашего брата там много</xt></xtg>
        </xg>
      </mg>
    </e>
  </entry>

  <entry exclude="fst">
    <lemma>мийӧ</lemma>

    <stem></stem>

    <contlex>PRON-PERS-PL1-NOM</contlex>

    <pos>PRON-PERS</pos>

    <e>
      <mg>
        <m>
          <head></head>

          <tg lang="ru"><t></t></tg>
        </m>
      </mg>
    </e>
  </entry>

  <entry exclude="fst">
    <lemma>митӧг</lemma>

    <stem></stem>

    <contlex>PRON-PERS-PL1-CAR</contlex>

    <pos>PRON-PERS</pos>

    <e>
      <mg>
        <m>
          <head></head>

          <tg lang="ru"><t pos="PRON-PERS">без нас</t></tg>

          <assoc MNo="1" assocType="see" lemmaID="миянтӧг_PRON-PERS"></assoc>
        </m>

        <xg>
          <x>митӧг тай тані эштӧдчӧны</x>

          <xtg lang="ru"><xt>и без нас тут заканчивают</xt></xtg>
        </xg>
      </mg>
    </e>
  </entry>

  <entry exclude="fst">
    <lemma>миян</lemma>

    <stem></stem>

    <contlex>PRON-PERS-PL1-GEN</contlex>

    <pos>PRON-PERS</pos>

    <e>
      <mg>
        <m>
          <head><!-- <tg lang="ru"><t pos="PRON-PERS"><b>(миян</b> <i>- полная основа в косв. п. и в конструкциях с послелогами)</i> <i>мест.</i> мы</t></tg> --></head>

          <tg lang="ru"><t></t>полная основа в косв. п. и в конструкциях с
          послелогами мест. мы</tg>
        </m>

        <xg>
          <x>миян вылӧ</x>

          <xtg lang="ru"><xt pos="PRON-PERS">на нас</xt></xtg>
        </xg>

        <xg>
          <x>миян йылысь</x>

          <xtg lang="ru"><xt pos="PRON-PERS">о нас</xt></xtg>
        </xg>

        <xg>
          <x>бабӧ видзӧдӧ миян вылӧ жугыль синъясӧн</x>

          <xtg lang="ru"><xt pos="PRON-PERS">бабушка смотрит на нас печальными
          глазами</xt></xtg>
        </xg>

        <xg>
          <x>быдӧн миян дор</x>

          <xtg lang="ru"><xt pos="PRON-PERS">все за нас</xt></xtg>
        </xg>
      </mg>

      <mg>
        <m>
          <head></head>

          <tg lang="ru"><t></t></tg>
        </m>

        <xg>
          <x>миян вӧлі бабӧ да ещӧ дед</x>

          <xtg lang="ru"><xt pos="PRON-PERS">у нас были бабушка да ещё и
          дед</xt></xtg>
        </xg>

        <xg>
          <x>миян ставыс на лючки-ладнӧ</x>

          <xtg lang="ru"><xt pos="PRON-PERS">у нас пока всё
          благополучно</xt></xtg>
        </xg>

        <xg>
          <x>миян пӧ няньыс тэкӧд шӧрыштӧма, шыд-рокыс пусьӧма, межаыс
          юкӧма</x>

          <xtg lang="ru"><xt>нам спорить не о чем</xt></xtg>

          <literal>
            <tg lang="ru"><t>у нас с тобой коврига нарезана, суп-каша сварены,
            земля отмежевана</t></tg>
          </literal>
        </xg>
      </mg>

      <mg>
        <m>
          <head></head>

          <tg lang="ru"><t pos="PRON-PERS">наш</t></tg>
        </m>

        <xg>
          <x>миян батьяс да пӧльяс</x>

          <xtg lang="ru"><xt pos="PRON-PERS">наши отцы и деды</xt></xtg>
        </xg>

        <xg>
          <x>миян йӧз</x>

          <xtg lang="ru"><xt pos="PRON-PERS">наши люди</xt></xtg>
        </xg>

        <xg>
          <x>миян ныв-пи</x>

          <xtg lang="ru"><xt pos="PRON-PERS">наши дети</xt></xtg>
        </xg>

        <xg>
          <x>миян пыж</x>

          <xtg lang="ru"><xt pos="PRON-PERS">наша лодка</xt></xtg>
        </xg>
      </mg>
    </e>
  </entry>

  <entry exclude="fst">
    <lemma>миянкӧд</lemma>

    <stem></stem>

    <contlex>PRON-PERS-PL1-COM</contlex>

    <pos>PRON-PERS</pos>

    <e>
      <mg>
        <m>
          <head></head>

          <tg lang="ru"><t></t></tg>
        </m>

        <xg>
          <x>тэ миянкӧд эн вензьы</x>

          <xtg lang="ru"><xt pos="PRON-PERS">ты с нами не спорь</xt></xtg>
        </xg>

        <xg>
          <x>сійӧ кольччис горт овны миянкӧд</x>

          <xtg lang="ru"><xt pos="PRON-PERS">она осталась с нами
          домовничать</xt></xtg>
        </xg>
      </mg>

      <mg>
        <m>
          <head></head>

          <tg lang="ru"><t pos="PRON-PERS">с нами, с нашим домом</t></tg>
        </m>

        <xg>
          <x>керка, коді сулалӧ дзик миянкӧд воча</x>

          <xtg lang="ru"><xt pos="PRON-PERS">дом, который стоит прямо напротив
          нашего</xt></xtg>
        </xg>
      </mg>
    </e>
  </entry>

  <entry exclude="fst">
    <lemma>миянла</lemma>

    <stem></stem>

    <contlex>PRON-PERS-PL1-CNS</contlex>

    <pos>PRON-PERS</pos>

    <e>
      <mg>
        <m>
          <head></head>

          <tg lang="ru"><t></t></tg>
        </m>

        <xg>
          <x>миянла кӧсйӧмаӧсь ыстыны машина</x>

          <xtg lang="ru"><xt pos="PRON-PERS">за нами обещали прислать
          машину</xt></xtg>
        </xg>
      </mg>
    </e>
  </entry>

  <entry exclude="fst">
    <lemma>миянлань</lemma>

    <stem></stem>

    <contlex>PRON-PERS-PL1-APR</contlex>

    <pos>PRON-PERS</pos>

    <e>
      <mg>
        <m>
          <head><com>прибл. п. от миян</com></head>

          <tg lang="ru"><t></t></tg>
        </m>

        <xg>
          <x>кодкӧ со миянлань локтӧ</x>

          <xtg lang="ru"><xt pos="PRON-PERS">кто-то, смотри, к нам, в нашу
          сторону идёт</xt></xtg>
        </xg>

        <xg>
          <x>сійӧ зумыша видзӧдліс миянлань</x>

          <xtg lang="ru"><xt pos="PRON-PERS">он хмуро посмотрел в нашу
          сторону</xt></xtg>
        </xg>
      </mg>
    </e>
  </entry>

  <entry exclude="fst">
    <lemma>миянлы</lemma>

    <stem></stem>

    <contlex>PRON-PERS-PL1-DAT</contlex>

    <pos>PRON-PERS</pos>

    <e>
      <mg>
        <m>
          <head></head>

          <tg lang="ru"><t></t></tg>
        </m>

        <xg>
          <x>ми асьным тӧдам, мый миянлы вӧчны</x>

          <xtg lang="ru"><xt pos="PRON-PERS">мы сами знаем, что нам
          делать</xt></xtg>
        </xg>

        <xg>
          <x>миянлы воссис паськыд туй</x>

          <xtg lang="ru"><xt pos="PRON-PERS">перед нами открылась широкая
          дорога</xt></xtg>
        </xg>
      </mg>
    </e>
  </entry>

  <entry exclude="fst">
    <lemma>миянлысь</lemma>

    <stem></stem>

    <contlex>PRON-PERS-PL1-ABL</contlex>

    <pos>PRON-PERS</pos>

    <e>
      <mg>
        <m>
          <head></head>

          <tg lang="ru"><t></t></tg>
        </m>

        <xg>
          <x>тэ миянлысь юав</x>

          <xtg lang="ru"><xt pos="PRON-PERS">ты у нас спроси</xt></xtg>
        </xg>
      </mg>

      <mg>
        <m>
          <head></head>

          <tg lang="ru"><t pos="PRON-PERS">наш</t></tg>
        </m>

        <xg>
          <x>миянлысь удж ошкӧны быдӧн</x>

          <xtg lang="ru"><xt pos="PRON-PERS">нашу работу все хвалят</xt></xtg>
        </xg>
      </mg>
    </e>
  </entry>

  <entry exclude="fst">
    <lemma>миянлӧн</lemma>

    <stem></stem>

    <contlex>PRON-PERS-PL1-GEN</contlex>

    <pos>PRON-PERS</pos>

    <e>
      <mg>
        <m>
          <head></head>

          <tg lang="ru"><t></t></tg>

          <assoc MNo="1" assocType="see">миян</assoc>
        </m>

        <xg>
          <x>миянлӧн кодь</x>

          <xtg lang="ru"><xt pos="PRON-PERS">как у нас, как наш</xt></xtg>
        </xg>

        <xg>
          <x>тайӧ мӧскыс дзик миянлӧн кодь</x>

          <xtg lang="ru"><xt pos="PRON-PERS">эта корова совсем как
          наша</xt></xtg>
        </xg>
      </mg>
    </e>
  </entry>

  <entry exclude="fst">
    <lemma>миянсянь</lemma>

    <stem></stem>

    <contlex>PRON-PERS-PL1-EGR</contlex>

    <pos>PRON-PERS</pos>

    <e>
      <mg>
        <m>
          <head></head>

          <tg lang="ru"><t pos="PRON-PERS">от нас</t></tg>
        </m>

        <xg>
          <x>виччысьӧны миянсянь отсӧг</x>

          <xtg lang="ru"><xt pos="PRON-PERS">они ждут от нас помощи</xt></xtg>
        </xg>

        <xg>
          <x>мый миянсянь колӧ?</x>

          <xtg lang="ru"><xt pos="PRON-PERS">что тебе от нас надо?</xt></xtg>
        </xg>
      </mg>

      <mg>
        <m>
          <head></head>

          <tg lang="ru"><t pos="PRON-PERS">от нас,</t><t pos="PRON-PERS">от
          нашего дома</t></tg>
        </m>

        <xg>
          <x>миянсянь кык керка сайын</x>

          <xtg lang="ru"><xt pos="PRON-PERS">через два дома от нас</xt></xtg>
        </xg>
      </mg>
    </e>
  </entry>

  <entry exclude="fst">
    <lemma>миянтӧг</lemma>

    <stem></stem>

    <contlex>PRON-PERS-PL1-CAR</contlex>

    <pos>PRON-PERS</pos>

    <e>
      <mg>
        <m>
          <head></head>

          <tg lang="ru"><t pos="PRON-PERS">без нас</t></tg>
        </m>

        <xg>
          <x>миянтӧг он вермы овны</x>

          <xtg lang="ru"><xt pos="PRON-PERS">без нас ты не
          обойдёшься</xt></xtg>
        </xg>
      </mg>
    </e>
  </entry>

  <entry exclude="fst">
    <lemma>миянын</lemma>

    <stem></stem>

    <contlex>PRON-PERS-PL1-INE</contlex>

    <pos>PRON-PERS</pos>

    <e>
      <mg>
        <m>
          <head></head>

          <tg lang="ru"><t pos="PRON-PERS">у нас,</t><t pos="PRON-PERS">в
          нашем доме</t></tg>
        </m>

        <xg>
          <x>патеранас агроном миянын олӧ</x>

          <xtg lang="ru"><xt pos="PRON-PERS">агроном живёт у нас на
          квартире</xt></xtg>
        </xg>
      </mg>

      <mg>
        <m>
          <head></head>

          <tg lang="ru"><t></t></tg>
        </m>

        <xg>
          <x>делӧыс абу миянын</x>

          <xtg lang="ru"><xt pos="PRON-PERS">не в нас дело</xt></xtg>
        </xg>
      </mg>
    </e>
  </entry>

  <entry exclude="fst">
    <lemma>миянӧ</lemma>

    <stem></stem>

    <contlex>PRON-PERS-PL1-ILL</contlex>

    <pos>PRON-PERS</pos>

    <e>
      <mg>
        <m>
          <head></head>

          <tg lang="ru"><t pos="PRON-PERS">к нам,</t><t pos="PRON-PERS">в наш
          дом</t></tg>
        </m>

        <xg>
          <x>кодкӧ миянӧ локтӧ</x>

          <xtg lang="ru"><xt pos="PRON-PERS">кто-то к нам (в наш дом)
          идёт</xt></xtg>
        </xg>
      </mg>
    </e>
  </entry>

  <entry exclude="fst">
    <lemma>миянӧдз</lemma>

    <stem></stem>

    <contlex>PRON-PERS-PL1-TER</contlex>

    <pos>PRON-PERS</pos>

    <e>
      <mg>
        <m>
          <head></head>

          <tg lang="ru"><t></t></tg>
        </m>

        <xg>
          <x>тэныд миянӧдз кутшӧм мог?</x>

          <xtg lang="ru"><xt pos="PRON-PERS">какое тебе до нас
          дело?</xt></xtg>
        </xg>

        <xg>
          <x>ылын кӧнкӧ мунӧ войнаыд, а йӧлӧгаыс сылӧн локтӧ миянӧдз</x>

          <xtg lang="ru"><xt pos="PRON-PERS">далеко где-то идёт война, а эхо
          её доходит до нас</xt></xtg>
        </xg>
      </mg>
    </e>
  </entry>

  <entry exclude="fst">
    <lemma>миянӧс</lemma>

    <stem></stem>

    <contlex>PRON-PERS-PL1-ACC</contlex>

    <pos>PRON-PERS</pos>

    <e>
      <mg>
        <m>
          <head></head>

          <tg lang="ru"><t pos="PRON-PERS">нас</t></tg>
        </m>

        <xg>
          <x>тэ миянӧс эн велӧд</x>

          <xtg lang="ru"><xt pos="PRON-PERS">ты нас не учи</xt></xtg>
        </xg>
      </mg>
    </e>
  </entry>

  <entry exclude="fst">
    <lemma>на</lemma>

    <stem></stem>

    <contlex>PRON-PERS-PL3-NOM</contlex>

    <pos>PRON-PERS</pos>

    <e>
      <mg>
        <m>
          <head><com>употр. в косв. падежах и в послел.
          конструкциях</com></head>

          <tg lang="ru"><t></t></tg>
        </m>

        <xg>
          <x>на дырйи</x>

          <xtg lang="ru"><xt pos="ADV" sem="advl-spat">при них
          присутствии</xt></xtg>

          <xtg lang="ru"><xt pos="ADV" sem="advl-spat">в их
          присутствии</xt></xtg>
        </xg>

        <xg>
          <x>на моз</x>

          <xtg lang="ru"><xt pos="PREP" sem="compStand">как они,</xt></xtg>

          <xtg lang="ru"><xt pos="PREP" sem="compStand">подобно им</xt></xtg>
        </xg>

        <xg>
          <x>на пиысь</x>

          <xtg lang="ru"><xt pos="PREP">из них</xt></xtg>

          <xtg lang="ru"><xt>из их среды</xt></xtg>
        </xg>

        <xg>
          <x>на вылӧ эн надейтчы</x>

          <xtg lang="ru"><xt>на них не надейся</xt></xtg>
        </xg>

        <xg>
          <x>на йылысь эн казьтыв</x>

          <xtg lang="ru"><xt>о них не вспоминай</xt></xtg>
        </xg>
      </mg>

      <mg>
        <m>
          <head><com>редко в роли притяж. мест.</com></head>

          <tg lang="ru"><t pos="PRON-PERS">их</t></tg>
        </m>

        <xg>
          <x>на керкаын</x>

          <xtg lang="ru"><xt sem="advl-spat">в их доме</xt></xtg>
        </xg>

        <xg>
          <x>на удж бӧрся видзӧдны колӧ</x>

          <xtg lang="ru"><xt>надо следить за их работой</xt></xtg>
        </xg>
      </mg>
    </e>
  </entry>

  <entry exclude="fst">
    <lemma>найӧ</lemma>

    <stem></stem>

    <contlex>PRON-PERS-PL3-NOM</contlex>

    <pos>PRON-PERS</pos>

    <e>
      <mg>
        <m>
          <head></head>

          <tg lang="ru"><t pos="PRON-PERS">они</t></tg>
        </m>

        <xg>
          <x>найӧ талун локтасны</x>

          <xtg lang="ru"><xt>они сегодня придут</xt></xtg>
        </xg>

        <xg type="saying">
          <x>найӧ коркӧ паньӧн вежсьылӧмаӧсь</x>

          <xtg lang="ru"><xt>они когда-то ложками обменялись</xt><re>повод к чему-л., напр., для посещений</re></xtg>
        </xg>
      </mg>

      <mg>
        <m>
          <head><com>редко употр. в роли притяж. мест.</com></head>

          <tg lang="ru"><t pos="PRON-PERS">их</t></tg>
        </m>

        <xg>
          <x>найӧ вӧлӧн локті</x>

          <xtg lang="ru"><xt>я приехал на их лошади</xt></xtg>
        </xg>

        <xg>
          <x>найӧ уджысь ме кыв ог кут</x>

          <xtg lang="ru"><xt>за их работу я не в ответе</xt></xtg>
        </xg>
      </mg>
    </e>
  </entry>

  <entry exclude="fst">
    <lemma>найӧс</lemma>

    <stem></stem>

    <contlex>PRON-PERS-PL3-ACC</contlex>

    <pos>PRON-PERS</pos>

    <e>
      <mg>
        <m>
          <head></head>

          <tg lang="ru"><t></t></tg>
        </m>

        <xg>
          <x>ме найӧс талун эг аддзыв</x>

          <xtg lang="ru"><xt>сегодня я их не видел</xt></xtg>
        </xg>

        <xg>
          <x>найӧс ме бура тӧда</x>

          <xtg lang="ru"><xt>я их хорошо знаю</xt></xtg>
        </xg>
      </mg>
    </e>
  </entry>

  <entry exclude="fst">
    <lemma>налы</lemma>

    <stem></stem>

    <contlex>PRON-PERS-PL3-DAT</contlex>

    <pos>PRON-PERS</pos>

    <e>
      <mg>
        <m>
          <head></head>

          <tg lang="ru"><t></t></tg>
        </m>

        <xg>
          <x>ме налы петкӧдла!</x>

          <xtg lang="ru"><xt>я им покажу!</xt></xtg>
        </xg>
      </mg>
    </e>
  </entry>

  <entry exclude="fst">
    <lemma>налысь</lemma>

    <stem></stem>

    <contlex>PRON-PERS-PL3-ABL</contlex>

    <pos>PRON-PERS</pos>

    <e>
      <mg>
        <m>
          <head></head>

          <tg lang="ru"><t pos="PRON-PERS">их</t></tg>
        </m>

        <xg>
          <x>налысь керкасӧ тэ тӧдан?</x>

          <xtg lang="ru"><xt>ты знаешь их дом?</xt></xtg>
        </xg>

        <xg>
          <x>налысь писӧ аддзылін?</x>

          <xtg lang="ru"><xt>ты видел их сына?</xt></xtg>
        </xg>
      </mg>

      <mg>
        <m>
          <head></head>

          <tg lang="ru"><t></t></tg>
        </m>

        <xg>
          <x>налы кӧ сетін, налысь и кор</x>

          <xtg lang="ru"><xt>если отдал им, у них и проси</xt></xtg>
        </xg>
      </mg>
    </e>
  </entry>

  <entry exclude="fst">
    <lemma>налӧн</lemma>

    <stem></stem>

    <contlex>PRON-PERS-PL3-GEN</contlex>

    <pos>PRON-PERS</pos>

    <e>
      <mg>
        <m>
          <head></head>

          <tg lang="ru"><t pos="PRON-PERS">их</t></tg>
        </m>

        <xg>
          <x>налӧн керканыс чукыль саяс</x>

          <xtg lang="ru"><xt>их дом за поворотом</xt></xtg>
        </xg>

        <xg>
          <x>тайӧ тіян? — Абу, тайӧ налӧн</x>

          <xtg lang="ru"><xt>это ваше? — Нет, это их</xt></xtg>
        </xg>

        <xg type="saying">
          <x>налӧн вашкӧдчӧмыс орчча сиктӧдз юралӧ</x>

          <xtg lang="ru"><xt>их перешёптывание доносится до соседней
          деревни</xt></xtg>
        </xg>
      </mg>

      <mg>
        <m>
          <head></head>

          <tg lang="ru"><t></t></tg>
        </m>

        <xg>
          <x>код налӧн быдмӧ, ныв али пи?</x>

          <xtg lang="ru"><xt>кто у них растёт, дочь или сын?</xt></xtg>
        </xg>
      </mg>
    </e>
  </entry>

  <entry exclude="fst">
    <lemma>наын</lemma>

    <stem></stem>

    <contlex>PRON-PERS-PL3-INE</contlex>

    <pos>PRON-PERS</pos>

    <e>
      <mg>
        <m>
          <head></head>

          <tg lang="ru"><t></t></tg>
        </m>

        <xg>
          <x>делӧыс абу наын</x>

          <xtg lang="ru"><xt>не в них дело</xt></xtg>
        </xg>
      </mg>
    </e>
  </entry>

  <entry exclude="fst">
    <lemma>наысь</lemma>

    <stem></stem>

    <contlex>PRON-PERS-PL3-ELA</contlex>

    <pos>PRON-PERS</pos>

    <e>
      <mg>
        <m>
          <head></head>

          <tg lang="ru"><t></t></tg>
        </m>

        <xg>
          <x>мый меным наысь</x>

          <xtg lang="ru"><xt>что мне в них</xt></xtg>
        </xg>
      </mg>
    </e>
  </entry>

  <entry exclude="fst">
    <lemma>сы</lemma>

    <stem></stem>

    <contlex>PRON-PERS-SG3-OBL</contlex>

    <pos>PRON-PERS</pos>

    <e>
      <mg>
        <m>
          <head></head>

          <tg lang="ru"><t pos="PRON-PERS">он</t><t pos="PRON-PERS">она</t><t
          pos="PRON-PERS">оно</t></tg>
        </m>

        <xg>
          <x>сы вылын выль дӧрӧм</x>

          <xtg lang="ru"><xt>на нём новая рубашка</xt></xtg>
        </xg>

        <xg>
          <x>сы дырйи абу гажтӧм</x>

          <xtg lang="ru"><xt>при нём не скучно</xt></xtg>

          <xtg lang="ru"><xt>при ней не скучно</xt></xtg>
        </xg>

        <xg>
          <x>сы моз вӧчны</x>

          <xtg lang="ru"><xt>сделать как он</xt></xtg>

          <xtg lang="ru"><xt>сделать как она</xt></xtg>

          <xtg lang="ru"><xt>сделать как оно</xt></xtg>
        </xg>

        <xg>
          <x>сы бӧрын</x>

          <xtg lang="ru"><xt>затем</xt></xtg>
        </xg>

        <xg>
          <x>сы вӧсна</x>

          <xtg lang="ru"><xt>потому, поэтому, с этой целью</xt></xtg>
        </xg>

        <xg>
          <x>сы вӧсна, мый...</x>

          <xtg lang="ru"><xt>потому что ...</xt></xtg>
        </xg>
      </mg>

      <mg>
        <m>
          <head><com>редко в роли притяж. мест.</com></head>

          <tg lang="ru"><t pos="PRON-PERS">его</t><t
          pos="PRON-PERS">её</t></tg>
        </m>

        <xg>
          <x>сы син водзын</x>

          <xtg lang="ru"><xt>на его глазах</xt></xtg>
        </xg>

        <xg>
          <x>сы шӧрӧ</x>

          <xtg lang="ru"><xt>к несчастью</xt></xtg>

          <xtg lang="ru"><xt>на беду</xt></xtg>
        </xg>
      </mg>

      <mg>
        <m>
          <head><range>диал.</range></head>

          <tg lang="ru"><t></t></tg>
        </m>

        <xg>
          <x>сы сьӧкыд</x>

          <xtg lang="ru"><xt>так тяжёл</xt></xtg>
        </xg>

        <assoc MNo="1" assocType="see">сэтшӧм</assoc>
      </mg>
    </e>
  </entry>

  <entry>
    <lemma>сыа-мэа</lemma>

    <stem></stem>

    <contlex>PRON-DUAL</contlex>

    <pos>PRON-PERS</pos>

    <e>
      <mg>
        <m>
          <head><com>взаимн.</com></head>

          <tg lang="ru"><t pos="PRON-PERS">мы кроме тебя</t></tg>
        </m>

        <xg>
          <x>Сыа-меа костын</x>

          <xtg lang="ru"><xt>между нами</xt></xtg>
        </xg>
      </mg>
    </e>
  </entry>

  <entry exclude="fst">
    <lemma>сыкӧд</lemma>

    <stem></stem>

    <contlex>PRON-PERS-SG3-COM</contlex>

    <pos>PRON-PERS</pos>

    <e>
      <mg>
        <m>
          <head></head>

          <tg lang="ru"><t></t></tg>
        </m>

        <xg>
          <x>сыкӧд он гажтӧмтчы</x>

          <xtg lang="ru"><xt>с ним не соскучишься</xt><xt>с ней не
          соскучишься</xt></xtg>
        </xg>

        <xg>
          <x>сыкӧд тшӧтш</x>

          <xtg lang="ru"><xt>вместе с тем</xt></xtg>

          <xtg lang="ru"><xt> к тому же</xt></xtg>
        </xg>
      </mg>
    </e>
  </entry>

  <entry exclude="fst">
    <lemma>сыла</lemma>

    <stem></stem>

    <contlex>PRON-PERS-SG3-CNS</contlex>

    <pos>PRON-PERS</pos>

    <e>
      <mg>
        <m>
          <head></head>

          <tg lang="ru"><t></t></tg>
        </m>

        <xg>
          <x>сыла ветлісны</x>

          <xtg lang="ru"><xt>за ним сходили</xt></xtg>

          <xtg lang="ru"><xt>за нею сходили</xt></xtg>
        </xg>
      </mg>
    </e>
  </entry>

  <entry exclude="fst">
    <lemma>сылань</lemma>

    <stem></stem>

    <contlex>PRON-PERS-SG3-APR</contlex>

    <pos>PRON-PERS</pos>

    <e>
      <mg>
        <m>
          <head></head>

          <tg lang="ru"><t>туда, в том направлении</t></tg>

          <assoc assocType="see">сійӧ</assoc>
        </m>

        <xg>
          <x>сылань мунны</x>

          <xtg lang="ru"><xt>идти в том направлении</xt></xtg>
        </xg>

        <xg>
          <x>сылань матыстчыны</x>

          <xtg lang="ru"><xt>подойти к нему</xt></xtg>

          <xtg lang="ru"><xt>подойти к ней</xt></xtg>
        </xg>
      </mg>
    </e>
  </entry>

  <entry exclude="fst">
    <lemma>сыланьӧ</lemma>

    <stem></stem>

    <contlex>PRON-PERS-SG3-APR-ILL</contlex>

    <pos>PRON-PERS</pos>

    <e>
      <mg>
        <m>
          <head></head>

          <tg lang="ru"><t></t></tg>
        </m>

        <assoc assocType="see">сылань</assoc>
      </mg>
    </e>
  </entry>

  <entry exclude="fst">
    <lemma>сыланьысь</lemma>

    <stem></stem>

    <contlex>PRON-PERS-SG3-APR-ELA</contlex>

    <pos>PRON-PERS</pos>

    <e>
      <mg>
        <m>
          <head></head>

          <tg lang="ru"><t>оттуда, с той стороны</t></tg>
        </m>

        <xg>
          <x>сыланьысь жӧ кыліс нывъяслӧн сьылӧм</x>

          <xtg lang="ru"><xt>оттуда же было слышно пение девушек</xt></xtg>
        </xg>
      </mg>
    </e>
  </entry>

  <entry exclude="fst">
    <lemma>сылы</lemma>

    <stem></stem>

    <contlex>PRON-PERS-SG3-DAT</contlex>

    <pos>PRON-PERS</pos>

    <e>
      <mg>
        <m>
          <head></head>

          <tg lang="ru"><t></t></tg>
        </m>

        <xg>
          <x>мойвиис</x>

          <xtg lang="ru"><xt>ему повезло</xt></xtg>

          <xtg lang="ru"><xt>ей повезло</xt></xtg>
        </xg>
      </mg>
    </e>
  </entry>

  <entry exclude="fst">
    <lemma>сылысь</lemma>

    <stem></stem>

    <contlex>PRON-PERS-SG3-ABL</contlex>

    <pos>PRON-PERS</pos>

    <e>
      <mg>
        <m>
          <head></head>

          <tg lang="ru"><t></t></tg>
        </m>

        <xg>
          <x>юав сылысь</x>

          <xtg lang="ru"><xt>спроси у него</xt></xtg>

          <xtg lang="ru"><xt>спроси у неё</xt></xtg>
        </xg>

        <xg>
          <x>~ и тӧлын лым он босьт</x>

          <xtg lang="ru"><xt>у него и зимой снега не выпросишь</xt><re>о скупом человеке</re></xtg>
        </xg>
      </mg>

      <mg>
        <m>
          <head></head>

          <tg lang="ru"><t></t></tg>
        </m>

        <xg>
          <x>~ книга ме эг аддзыв</x>

          <xtg lang="ru"><xt>его книгу я не видел</xt></xtg>
        </xg>
      </mg>
    </e>
  </entry>

  <entry exclude="fst">
    <lemma>сылӧн</lemma>

    <stem></stem>

    <contlex>PRON-PERS-SG3-GEN</contlex>

    <pos>PRON-PERS</pos>

    <e>
      <mg>
        <m>
          <head></head>

          <tg lang="ru"><t>его</t></tg>

          <tg lang="ru"><t>её</t></tg>
        </m>

        <xg>
          <x>тайӧ пальтоыс сылӧн</x>

          <xtg lang="ru"><xt>это пальто его</xt></xtg>
        </xg>
      </mg>

      <mg>
        <m>
          <head></head>

          <tg lang="ru"><t></t></tg>
        </m>

        <xg>
          <x>сылӧн пиньыс висьӧ</x>

          <xtg lang="ru"><xt>у него болит зуб</xt></xtg>

          <xtg lang="ru"><xt>у неё болит зуб</xt></xtg>
        </xg>

        <xg>
          <x>сылӧн чунь помыс зарниа</x>

          <xtg lang="ru"><xt>у него руки золотые</xt></xtg>
        </xg>
      </mg>
    </e>
  </entry>

  <entry exclude="fst">
    <lemma>сысянь</lemma>

    <stem></stem>

    <contlex>PRON-PERS-SG3-EGR</contlex>

    <pos>PRON-PERS</pos>

    <e>
      <mg>
        <m>
          <head></head>

          <tg lang="ru"><t></t></tg>
        </m>

        <xg>
          <x>сысянь быдтор позьӧ виччысьны</x>

          <xtg lang="ru"><xt>от него всё можно ожидать</xt></xtg>

          <xtg lang="ru"><xt>от неё всё можно ожидать</xt></xtg>
        </xg>
      </mg>
    </e>
  </entry>

  <entry exclude="fst">
    <lemma>сытӧг</lemma>

    <stem></stem>

    <contlex>PRON-PERS-SG3-CAR</contlex>

    <pos>PRON-PERS</pos>

    <e>
      <mg>
        <m>
          <head></head>

          <tg lang="ru"><t></t></tg>
        </m>

        <xg>
          <x>нинӧм оз артмы</x>

          <xtg lang="ru"><xt>без него ничего не получится</xt></xtg>

          <xtg lang="ru"><xt>без неё ничего не получится</xt></xtg>
        </xg>
      </mg>
    </e>
  </entry>

  <entry exclude="fst">
    <lemma>сыысь</lemma>

    <stem></stem>

    <contlex>PRON-PERS-SG3-ELA</contlex>

    <pos>PRON-PERS</pos>

    <e>
      <mg>
        <m>
          <head></head>

          <tg lang="ru"><t></t></tg>
        </m>

        <xg>
          <x>сыысь он мын</x>

          <xtg lang="ru"><xt>от него не избавишься</xt></xtg>

          <xtg lang="ru"><xt>от неё не избавишься</xt></xtg>
        </xg>
      </mg>
    </e>
  </entry>

  <entry exclude="fst">
    <lemma>сыӧдз</lemma>

    <stem></stem>

    <contlex>PRON-PERS-SG3-TER</contlex>

    <pos>PRON-PERS</pos>

    <e>
      <mg>
        <m>
          <head></head>

          <tg lang="ru"><t></t></tg>
        </m>

        <xg>
          <x>сыӧдз некодлы абу мог</x>

          <xtg lang="ru"><xt>до него никому нет дела</xt></xtg>

          <xtg lang="ru"><xt>до неё никому нет дела</xt></xtg>
        </xg>
      </mg>
    </e>
  </entry>

  <entry exclude="fst">
    <lemma>сыӧн</lemma>

    <stem></stem>

    <contlex>PRON-PERS-SG3-INSTR</contlex>

    <pos>PRON-PERS</pos>

    <e>
      <mg>
        <m>
          <head></head>

          <tg lang="ru"><t></t></tg>
        </m>

        <xg>
          <x>сыӧн ставӧн дӧвӧленӧсь</x>

          <xtg lang="ru"><xt>им все довольны</xt></xtg>

          <xtg lang="ru"><xt>ей все довольны</xt></xtg>

          <xtg lang="ru"><xt>ею все довольны</xt></xtg>
        </xg>
      </mg>
    </e>
  </entry>

  <entry exclude="fst">
    <lemma>сійӧ</lemma>

    <stem></stem>

    <contlex>PRON-PERS-SG3-NOM</contlex>

    <pos>PRON-PERS</pos>

    <e>
      <mg>
        <m>
          <head><!-- сы — краткая основа в н-рых косвенных падежах и в послеложных конструкциях --></head>

          <tg lang="ru"><t pos="PRON-PERS">он</t><t pos="PRON-PERS">она</t><t
          pos="PRON-PERS">оно</t></tg>
        </m>
      </mg>
    </e>
  </entry>

  <entry exclude="fst">
    <lemma>сійӧс</lemma>

    <stem></stem>

    <contlex>PRON-PERS-SG3-ACC</contlex>

    <pos>PRON-PERS</pos>

    <e>
      <mg>
        <m>
          <head></head>

          <tg lang="ru"><t></t></tg>
        </m>

        <xg>
          <x>ме ог тӧд</x>

          <xtg lang="ru"><xt>его я не знаю</xt></xtg>

          <xtg lang="ru"><xt>её я не знаю</xt></xtg>
        </xg>
      </mg>
    </e>
  </entry>

  <entry exclude="fst">
    <lemma>та</lemma>

    <stem></stem>

    <contlex>PRON-PERS-SG3-NOM</contlex>

    <pos>PRON-PERS</pos>

    <e>
      <mg>
        <m>
          <head></head>

          <tg lang="ru"><t></t></tg>
        </m>
      </mg>
    </e>
  </entry>

  <entry exclude="fst">
    <lemma>тайӧ</lemma>

    <stem></stem>

    <contlex>PRON-PERS-SG3-NOM</contlex>

    <pos>PRON-PERS</pos>

    <e>
      <mg>
        <m>
          <head></head>

          <tg lang="ru"><t></t></tg>
        </m>
      </mg>
    </e>
  </entry>

  <entry exclude="fst">
    <lemma>тайӧяс</lemma>

    <stem></stem>

    <contlex>PRON-PERS-PL3-NOM</contlex>

    <pos>PRON-PERS</pos>

    <e>
      <mg>
        <m>
          <head></head>

          <tg lang="ru"><t></t></tg>
        </m>
      </mg>
    </e>
  </entry>

  <entry exclude="fst">
    <lemma>тэ</lemma>

    <stem></stem>

    <contlex>PRON-PERS-SG2-NOM</contlex>

    <pos>PRON-PERS</pos>

    <e>
      <mg>
        <m>
          <head><com>полная основа в нек-рых косв. п.</com></head>

          <tg lang="ru"><t pos="PRON-PERS">ты</t></tg>
        </m>

        <xg>
          <x>тэ выяджык али госаджык?</x>

          <xtg lang="ru"><xt pos="PRON-PERS">чем ты лучше других?</xt></xtg>
        </xg>
      </mg>

      <mg>
        <m>
          <head></head>

          <tg lang="ru"><t></t></tg>
        </m>

        <xg>
          <x>тэ вомысь да ен пельӧ</x>

          <xtg lang="ru"><xt pos="PRON-PERS">твоими бы устами да мёд
          пить</xt></xtg>

          <literal>
            <xtg lang="ru"><xt>из твоих уст до слуха бога</xt></xtg>
          </literal>
        </xg>
      </mg>

      <mg>
        <m>
          <head></head>

          <tg lang="ru"><t></t></tg>
        </m>

        <xg>
          <x>тэ ног</x>

          <xtg lang="ru"><xt pos="PRON-PERS">по-твоему</xt></xtg>
        </xg>

        <xg>
          <x>тэ ордӧ</x>

          <xtg lang="ru"><xt pos="PRON-PERS">к тебе</xt></xtg>
        </xg>

        <xg>
          <x>тэ сайӧ дзебся</x>

          <xtg lang="ru"><xt pos="PRON-PERS">спрячусь за тебя</xt></xtg>
        </xg>
      </mg>
    </e>
  </entry>

  <entry exclude="fst">
    <lemma>тэа-меатӧг</lemma>

    <stem></stem>

    <contlex>PRON-DUAL</contlex>

    <pos>PRON-PERS</pos>

    <e>
      <mg>
        <m>
          <head><com>взаимн.</com></head>

          <tg lang="ru"><t pos="PRON-PERS">без нас с тобой</t></tg>
        </m>
      </mg>
    </e>
  </entry>

  <entry exclude="fst">
    <lemma>тэа-меаӧс</lemma>

    <stem></stem>

    <contlex></contlex>

    <pos>PRON-PERS</pos>

    <e>
      <mg>
        <m>
          <head><com>взаимн.</com></head>

          <tg lang="ru"><t pos="PRON-PERS">нас с тобой</t></tg>
        </m>
      </mg>
    </e>
  </entry>

  <entry>
    <lemma>тэа-мэа</lemma>

    <stem></stem>

    <contlex>PRON-DUAL</contlex>

    <pos>PRON-PERS</pos>

    <e>
      <mg>
        <m>
          <head><com>взаимн.</com></head>

          <tg lang="ru"><t pos="PRON-PERS">мы с тобой</t></tg>
        </m>

        <xg>
          <x></x>

          <xtg lang="ru"><xt></xt></xtg>
        </xg>
      </mg>
    </e>
  </entry>

  <entry exclude="fst">
    <lemma>тэа-мэалы</lemma>

    <stem></stem>

    <contlex>PRON-DUAL</contlex>

    <pos>PRON-PERS</pos>

    <e>
      <mg>
        <m>
          <head><com>взаимн.</com></head>

          <tg lang="ru"><t pos="PRON-PERS">нам с тобой</t></tg>
        </m>
      </mg>
    </e>
  </entry>

  <entry exclude="fst">
    <lemma>тэа-мэалӧн</lemma>

    <stem></stem>

    <contlex>PRON-DUAL</contlex>

    <pos>PRON-PERS</pos>

    <e>
      <mg>
        <m>
          <head><com>взаимн.</com></head>

          <tg lang="ru"><t pos="PRON-PERS">у нас с тобой</t></tg>
        </m>

        <xg type="saying">
          <x>тэа-меалӧн шудыс кӧвтымын ва кодь: кыскигас польдӧма, а кыскан да
          немтор абу</x>

          <xtg lang="ru"><xt> счастье наше с тобой как вода в бредне: тянешь —
          набухло, а вытянешь — ничего нет</xt></xtg>
        </xg>
      </mg>
    </e>
  </entry>

  <entry exclude="fst">
    <lemma>тэд</lemma>

    <stem></stem>

    <contlex>PRON-PERS-SG2-DAT</contlex>

    <pos>PRON-PERS</pos>

    <e>
      <mg>
        <m>
          <head></head>

          <tg lang="ru"><t></t></tg>
        </m>
      </mg>
    </e>
  </entry>

  <entry exclude="fst">
    <lemma>тэкӧд</lemma>

    <stem></stem>

    <contlex></contlex>

    <pos>PRON-PERS</pos>

    <e>
      <mg>
        <m>
          <head></head>

          <tg lang="ru"><t></t></tg>
        </m>

        <xg>
          <x>тэкӧд ӧти пос вылӧ оз позь сувтны</x>

          <xtg lang="ru"><xt pos="PRON-PERS">с тобой каши не
          сваришь</xt></xtg>

          <literal>
            <xtg lang="ru"><xt>с тобой на одну ступеньку нельзя
            становиться</xt></xtg>
          </literal>
        </xg>

        <xg>
          <x>ветла тэкӧд</x>

          <xtg lang="ru"><xt pos="PRON-PERS">схожу с тобой</xt></xtg>
        </xg>
      </mg>
    </e>
  </entry>

  <entry exclude="fst">
    <lemma>тэла</lemma>

    <stem></stem>

    <contlex></contlex>

    <pos>PRON-PERS</pos>

    <e>
      <mg>
        <m>
          <head></head>

          <tg lang="ru"><t></t></tg>
        </m>

        <xg>
          <x>тэла локтім</x>

          <xtg lang="ru"><xt pos="PRON-PERS">мы пришли за тобой</xt></xtg>
        </xg>
      </mg>
    </e>
  </entry>

  <entry exclude="fst">
    <lemma>тэн</lemma>

    <stem></stem>

    <contlex>PRON-PERS-SG2-DAT</contlex>

    <pos>PRON-PERS</pos>

    <e>
      <mg>
        <m>
          <head></head>

          <tg lang="ru"><t></t></tg>
        </m>
      </mg>
    </e>
  </entry>

  <entry exclude="fst">
    <lemma>тэнад</lemma>

    <stem></stem>

    <contlex>PRON-PERS-SG2-GEN</contlex>

    <pos>PRON-PERS</pos>

    <e>
      <mg>
        <m>
          <head></head>

          <tg lang="ru"><t></t></tg>
        </m>

        <xg>
          <x>тэнад понйыд?</x>

          <xtg lang="ru"><xt pos="PRON-PERS">твоя собака?</xt></xtg>
        </xg>
      </mg>

      <mg>
        <m>
          <head></head>

          <tg lang="ru"><t pos="PRON-PERS">твой</t></tg>
        </m>

        <xg>
          <x>тэнад кепысь</x>

          <xtg lang="ru"><xt pos="PRON-PERS">твои варежки</xt></xtg>
        </xg>

        <xg>
          <x>тэнад кылыд чертӧг-пурттӧг юртӧ кералас</x>

          <xtg lang="ru"><xt pos="PRON-PERS">твоё слово без топора и ножа
          голову отсечёт</xt></xtg>
        </xg>

        <xg>
          <x>тэнад помысь</x>

          <xtg lang="ru"><xt pos="PRON-PERS">где уж тебе</xt></xtg>

          <xtg lang="ru"><xt pos="PRON-PERS">от тебя пользы не
          будет</xt></xtg>
        </xg>
      </mg>

      <mg>
        <m>
          <head></head>

          <tg lang="ru"><t></t></tg>
        </m>

        <xg>
          <x>тэнад понйыд?</x>

          <xtg lang="ru"><xt pos="PRON-PERS">твоя собака?</xt></xtg>
        </xg>
      </mg>
    </e>
  </entry>

  <entry exclude="fst">
    <lemma>тэнсьыд</lemma>

    <stem></stem>

    <contlex>PRON-PERS-SG2-ABL</contlex>

    <pos>PRON-PERS</pos>

    <e>
      <mg>
        <m>
          <head></head>

          <tg lang="ru"><t></t></tg>
        </m>

        <xg>
          <x>тэнсьыд он босьт</x>

          <xtg lang="ru"><xt pos="PRON-PERS">у тебя не возьмёшь</xt></xtg>
        </xg>
      </mg>

      <mg>
        <m>
          <head></head>

          <tg lang="ru"><t pos="PRON-PERS">твой</t></tg>
        </m>

        <xg>
          <x>тэнсьыд гижӧдтӧ сьӧкыд гӧгӧрвоны</x>

          <xtg lang="ru"><xt pos="PRON-PERS">твой почерк трудно
          разобрать</xt></xtg>
        </xg>
      </mg>
    </e>
  </entry>

  <entry exclude="fst">
    <lemma>тэныд</lemma>

    <stem></stem>

    <contlex>PRON-PERS-SG2-DAT</contlex>

    <pos>PRON-PERS</pos>

    <e>
      <mg>
        <m>
          <head></head>

          <tg lang="ru"><t></t></tg>
        </m>

        <xg>
          <x>тэныд вӧзъя</x>

          <xtg lang="ru"><xt pos="PRON-PERS">предлагаю тебе</xt></xtg>
        </xg>
      </mg>
    </e>
  </entry>

  <entry exclude="fst">
    <lemma>тэнӧ</lemma>

    <stem></stem>

    <contlex></contlex>

    <pos>PRON-PERS</pos>

    <e>
      <mg>
        <m>
          <head></head>

          <tg lang="ru"><t></t></tg>
        </m>

        <xg>
          <x>кора тэнӧ</x>

          <xtg lang="ru"><xt pos="PRON-PERS">прошу тебя</xt></xtg>
        </xg>
      </mg>
    </e>
  </entry>

  <entry exclude="fst">
    <lemma>тэтӧг</lemma>

    <stem></stem>

    <contlex></contlex>

    <pos>PRON-PERS</pos>

    <e>
      <mg>
        <m>
          <head></head>

          <tg lang="ru"><t></t></tg>
        </m>

        <xg>
          <x>тэтӧг оз мунны</x>

          <xtg lang="ru"><xt pos="PRON-PERS">без тебя не идут</xt></xtg>
        </xg>
      </mg>
    </e>
  </entry>

  <entry exclude="fst">
    <lemma>тэысь</lemma>

    <stem></stem>

    <contlex></contlex>

    <pos>PRON-PERS</pos>

    <e>
      <mg>
        <m>
          <head></head>

          <tg lang="ru"><t></t></tg>
        </m>

        <xg>
          <x>тэысь ог кут повны</x>

          <xtg lang="ru"><xt pos="PRON-PERS">тебя не буду бояться</xt></xtg>
        </xg>
      </mg>
    </e>
  </entry>

  <entry exclude="fst">
    <lemma>ті</lemma>

    <stem></stem>

    <contlex>PRON-PERS-PL2-NOM</contlex>

    <pos>PRON-PERS</pos>

    <e>
      <mg>
        <m>
          <head></head>

          <tg lang="ru"><t pos="PRON-PERS">вы</t><re>полная основа "тіян"</re></tg>

          <assoc stemID="тіян_PRON-PERS"></assoc>
        </m>

        <xg>
          <x>ті асьныд тӧданныд</x>

          <xtg lang="ru"><xt pos="PRON-PERS">вы сами знаете</xt></xtg>
        </xg>

        <xg>
          <x>ті кысь локтанныд?</x>

          <xtg lang="ru"><xt pos="PRON-PERS">вы откуда идёте?</xt></xtg>
        </xg>
      </mg>

      <mg>
        <m>
          <head></head>

          <tg lang="ru"><t></t></tg>
        </m>

        <xg>
          <x>Ті вок (ті коддьӧм)</x>

          <xtg lang="ru"><xt pos="PRON-PERS"><att>неодобр.</att>ваш
          брат</xt></xtg>
        </xg>
      </mg>
    </e>
  </entry>

  <entry exclude="fst">
    <lemma>тіян</lemma>

    <stem></stem>

    <contlex></contlex>

    <pos>PRON-PERS</pos>

    <e>
      <mg>
        <m>
          <head></head>

          <tg lang="ru"><t pos="PRON-PERS">ваш</t></tg>
        </m>

        <xg>
          <x>кӧн тіян юкмӧсыд?</x>

          <xtg lang="ru"><xt pos="PRON-PERS">где ваш колодец?</xt></xtg>
        </xg>

        <xg>
          <x>тіян лызьясыд век мавтасаӧсь</x>

          <xtg lang="ru"><xt>ваши собаки всегда накормлены; держать порох
          сухим </xt></xtg>

          <literal>
            <xtg lang="ru"><xt>у вас лыжи всегда смазаны</xt></xtg>
          </literal>
        </xg>

        <xg>
          <x>тіян служба — кывзысьны, а менам — не пыксьыны</x>

          <xtg lang="ru"><xt pos="PRON-PERS">ваша служба — слушаться, а моя —
          не сопротивляться</xt></xtg>
        </xg>
      </mg>
    </e>
  </entry>

  <entry exclude="fst">
    <lemma>тіянлы</lemma>

    <stem></stem>

    <contlex></contlex>

    <pos>PRON-PERS</pos>

    <e>
      <mg>
        <m>
          <head></head>

          <tg lang="ru"><t></t></tg>
        </m>

        <xg>
          <x>тіянлы ковмас висьтавны</x>

          <xtg lang="ru"><xt pos="PRON-PERS">вам придётся
          рассказать</xt></xtg>
        </xg>
      </mg>
    </e>
  </entry>

  <entry exclude="fst">
    <lemma>тіянтӧг</lemma>

    <stem></stem>

    <contlex></contlex>

    <pos>PRON-PERS</pos>

    <e>
      <mg>
        <m>
          <head></head>

          <tg lang="ru"><t></t></tg>
        </m>

        <xg>
          <x>тіянтӧг тайӧ оз артмы</x>

          <xtg lang="ru"><xt pos="PRON-PERS">без вас это не
          получится</xt></xtg>
        </xg>
      </mg>
    </e>
  </entry>

  <entry exclude="fst">
    <lemma>тіянысь</lemma>

    <stem></stem>

    <contlex></contlex>

    <pos>PRON-PERS</pos>

    <e>
      <mg>
        <m>
          <head></head>

          <tg lang="ru"><t></t></tg>
        </m>

        <xg>
          <x>тіянысь абу омӧльӧсь</x>

          <xtg lang="ru"><xt pos="PRON-PERS">не хуже вас</xt></xtg>
        </xg>
      </mg>
    </e>
  </entry>

  <entry exclude="fst">
    <lemma>тіянӧс</lemma>

    <stem></stem>

    <contlex></contlex>

    <pos>PRON-PERS</pos>

    <e>
      <mg>
        <m>
          <head></head>

          <tg lang="ru"><t></t></tg>
        </m>

        <xg>
          <x>тіянӧс ог босьтӧй</x>

          <xtg lang="ru"><xt pos="PRON-PERS">вас не возьмём</xt></xtg>
        </xg>
      </mg>
    </e>
  </entry>
</dict>
